{
    "analysis": {
        "avg_acc_test_teacher": 80.98379999999999,
        "std_acc_test_teacher": 1.2052635237225768,
        "avg_acc_test_student": 81.51900000000003,
        "std_acc_test_student": 0.7928206899827013,
        "avg_acc_test_distilled": 80.78370000000001,
        "std_acc_test_distilled": 1.200465107675968,
        "final_acc_test_distilled": 81.99,
        "final_acc_test_teacher": 82.62,
        "final_acc_test_student": 81.06,
        "sum_time_train_teacher": 267.8621578216553,
        "sum_time_train_student": 30.879498720169067,
        "sum_time_train_distilled": 177.0631968975067,
        "sum_time_test_teacher": 145.07693552970886,
        "sum_time_test_student": 6.627241849899292,
        "sum_time_test_distilled": 54.78651976585388,
        "avg_time_train_teacher": 2.6786215782165526,
        "avg_time_train_student": 0.3087949872016907,
        "avg_time_train_distilled": 1.7706319689750671,
        "avg_time_test_teacher": 1.4507693552970886,
        "avg_time_test_student": 0.06627241849899292,
        "avg_time_test_distilled": 0.5478651976585388,
        "total_time": 159.73384165763855,
        "num_clauses_dropped": 16421,
        "num_clauses_dropped_percentage": 82.10499999999999
    },
    "mutual_information": {
        "sklearn_teacher": 1.640116648320208,
        "sklearn_student": 2.294231332103482,
        "info_teacher": -0.3671054281631364,
        "info_student": 16.14443246140056,
        "info_distilled": 1059.6634733096073
    },
    "params": {
        "teacher_num_clauses": 2000,
        "student_num_clauses": 100,
        "T": 30,
        "s": 10.0,
        "teacher_epochs": 20,
        "student_epochs": 80,
        "downsample": 0.25,
        "weighted_clauses": true,
        "number_of_state_bits": 8,
        "combined_epochs": 100
    },
    "experiment_name": "ds",
    "timestamp": "2025-02-10 06:26:03",
    "id": "ds_tnc2000_snc100_T30_s10.0_te20_se80_downsample0.25",
    "results": {
        "acc_test_teacher": {
            "0": 78.44,
            "1": 76.38000000000001,
            "2": 79.09,
            "3": 78.24,
            "4": 78.92,
            "5": 78.83,
            "6": 78.84,
            "7": 79.88,
            "8": 78.89,
            "9": 76.42999999999999,
            "10": 79.97,
            "11": 79.89,
            "12": 79.97999999999999,
            "13": 79.22,
            "14": 79.86999999999999,
            "15": 80.67,
            "16": 79.35,
            "17": 81.3,
            "18": 80.65,
            "19": 80.58,
            "20": 81.46,
            "21": 80.92,
            "22": 80.55,
            "23": 80.47999999999999,
            "24": 80.72,
            "25": 80.4,
            "26": 80.46,
            "27": 80.71000000000001,
            "28": 80.64,
            "29": 81.47,
            "30": 81.08999999999999,
            "31": 80.03,
            "32": 81.08,
            "33": 81.41000000000001,
            "34": 79.01,
            "35": 81.46,
            "36": 81.08999999999999,
            "37": 81.52000000000001,
            "38": 81.33,
            "39": 81.28999999999999,
            "40": 81.72,
            "41": 80.16,
            "42": 81.78999999999999,
            "43": 82.13000000000001,
            "44": 82.07,
            "45": 82.01,
            "46": 81.04,
            "47": 80.47999999999999,
            "48": 81.41000000000001,
            "49": 80.97,
            "50": 80.95,
            "51": 82.07,
            "52": 81.71000000000001,
            "53": 81.45,
            "54": 81.35,
            "55": 81.06,
            "56": 82.59,
            "57": 81.38,
            "58": 81.72,
            "59": 81.83,
            "60": 81.56,
            "61": 81.41000000000001,
            "62": 80.47999999999999,
            "63": 82.78999999999999,
            "64": 81.07,
            "65": 82.54,
            "66": 82.45,
            "67": 81.58,
            "68": 81.17,
            "69": 81.98,
            "70": 81.64,
            "71": 82.96,
            "72": 82.11,
            "73": 80.9,
            "74": 81.99,
            "75": 82.63000000000001,
            "76": 79.62,
            "77": 81.91000000000001,
            "78": 82.35,
            "79": 81.66,
            "80": 82.19999999999999,
            "81": 81.58,
            "82": 81.41000000000001,
            "83": 80.72,
            "84": 81.43,
            "85": 81.47,
            "86": 81.86,
            "87": 81.19,
            "88": 81.73,
            "89": 81.39,
            "90": 82.12,
            "91": 82.06,
            "92": 81.72,
            "93": 81.23,
            "94": 80.75,
            "95": 81.36,
            "96": 81.64,
            "97": 81.32000000000001,
            "98": 81.35,
            "99": 82.62
        },
        "acc_test_student": {
            "0": 77.69,
            "1": 78.69,
            "2": 79.57,
            "3": 79.08,
            "4": 80.12,
            "5": 80.46,
            "6": 80.05,
            "7": 79.82000000000001,
            "8": 80.69,
            "9": 81.67999999999999,
            "10": 80.05,
            "11": 81.28999999999999,
            "12": 81.14,
            "13": 81.69999999999999,
            "14": 81.45,
            "15": 81.08,
            "16": 81.63,
            "17": 81.56,
            "18": 81.58,
            "19": 81.2,
            "20": 82.0,
            "21": 81.96,
            "22": 81.02000000000001,
            "23": 81.39,
            "24": 82.17999999999999,
            "25": 81.52000000000001,
            "26": 81.89999999999999,
            "27": 81.39,
            "28": 81.38,
            "29": 80.93,
            "30": 81.84,
            "31": 81.27,
            "32": 81.67999999999999,
            "33": 81.38,
            "34": 81.37,
            "35": 81.22,
            "36": 81.64,
            "37": 81.8,
            "38": 81.87,
            "39": 81.96,
            "40": 82.1,
            "41": 82.26,
            "42": 81.96,
            "43": 81.25,
            "44": 81.41000000000001,
            "45": 81.72,
            "46": 81.69,
            "47": 81.87,
            "48": 81.61,
            "49": 82.21000000000001,
            "50": 81.53,
            "51": 81.89,
            "52": 82.42,
            "53": 81.92,
            "54": 81.74,
            "55": 81.72,
            "56": 81.87,
            "57": 81.19,
            "58": 82.11,
            "59": 81.67999999999999,
            "60": 81.71000000000001,
            "61": 81.67999999999999,
            "62": 81.97,
            "63": 81.62,
            "64": 81.58,
            "65": 82.03,
            "66": 82.11,
            "67": 82.1,
            "68": 82.06,
            "69": 82.71,
            "70": 81.87,
            "71": 82.0,
            "72": 82.06,
            "73": 82.64,
            "74": 81.75,
            "75": 81.39,
            "76": 82.17,
            "77": 80.89,
            "78": 82.23,
            "79": 82.14,
            "80": 82.08,
            "81": 82.67,
            "82": 81.56,
            "83": 81.6,
            "84": 82.05,
            "85": 81.94,
            "86": 81.49,
            "87": 81.98,
            "88": 81.72,
            "89": 82.1,
            "90": 81.41000000000001,
            "91": 81.58,
            "92": 81.82000000000001,
            "93": 82.06,
            "94": 80.31,
            "95": 81.33,
            "96": 82.22,
            "97": 81.88,
            "98": 81.95,
            "99": 81.06
        },
        "acc_test_distilled": {
            "0": 78.44,
            "1": 76.38000000000001,
            "2": 79.09,
            "3": 78.24,
            "4": 78.92,
            "5": 78.83,
            "6": 78.84,
            "7": 79.88,
            "8": 78.89,
            "9": 76.42999999999999,
            "10": 79.97,
            "11": 79.89,
            "12": 79.97999999999999,
            "13": 79.22,
            "14": 79.86999999999999,
            "15": 80.67,
            "16": 79.35,
            "17": 81.3,
            "18": 80.65,
            "19": 80.58,
            "20": 77.58,
            "21": 79.12,
            "22": 79.16,
            "23": 79.31,
            "24": 79.75,
            "25": 80.23,
            "26": 79.96,
            "27": 80.17999999999999,
            "28": 79.02,
            "29": 80.61,
            "30": 80.31,
            "31": 80.75,
            "32": 80.16,
            "33": 80.25999999999999,
            "34": 81.47,
            "35": 81.39,
            "36": 80.86,
            "37": 80.9,
            "38": 81.39,
            "39": 80.58,
            "40": 81.82000000000001,
            "41": 81.17,
            "42": 80.97,
            "43": 81.63,
            "44": 81.13,
            "45": 81.3,
            "46": 81.47999999999999,
            "47": 80.93,
            "48": 81.76,
            "49": 81.58999999999999,
            "50": 81.99,
            "51": 81.8,
            "52": 81.6,
            "53": 80.97,
            "54": 81.31,
            "55": 81.77,
            "56": 81.94,
            "57": 81.28,
            "58": 81.8,
            "59": 81.12,
            "60": 80.36,
            "61": 81.28,
            "62": 81.06,
            "63": 81.96,
            "64": 81.78999999999999,
            "65": 81.98,
            "66": 81.95,
            "67": 80.75,
            "68": 80.53,
            "69": 81.69999999999999,
            "70": 80.81,
            "71": 81.72,
            "72": 81.10000000000001,
            "73": 81.47,
            "74": 81.52000000000001,
            "75": 81.35,
            "76": 81.07,
            "77": 81.85,
            "78": 81.17999999999999,
            "79": 81.73,
            "80": 81.73,
            "81": 81.67999999999999,
            "82": 81.53,
            "83": 81.51,
            "84": 81.24,
            "85": 81.69999999999999,
            "86": 81.94,
            "87": 81.05,
            "88": 81.39,
            "89": 81.99,
            "90": 81.96,
            "91": 81.54,
            "92": 81.22,
            "93": 81.73,
            "94": 81.71000000000001,
            "95": 82.27,
            "96": 81.6,
            "97": 81.39,
            "98": 82.27,
            "99": 81.99
        },
        "time_train_teacher": {
            "0": 3.3271644115448,
            "1": 3.0698118209838867,
            "2": 2.997260808944702,
            "3": 2.9647226333618164,
            "4": 2.9367573261260986,
            "5": 2.918020009994507,
            "6": 2.9009945392608643,
            "7": 2.87103271484375,
            "8": 2.8527984619140625,
            "9": 2.825275182723999,
            "10": 2.810131072998047,
            "11": 2.8129384517669678,
            "12": 2.8103549480438232,
            "13": 2.76354718208313,
            "14": 2.75774884223938,
            "15": 2.756988048553467,
            "16": 2.748448133468628,
            "17": 2.7389557361602783,
            "18": 2.742464780807495,
            "19": 2.7288050651550293,
            "20": 2.7315428256988525,
            "21": 2.715670585632324,
            "22": 2.71439790725708,
            "23": 2.7077221870422363,
            "24": 2.7112646102905273,
            "25": 2.6919660568237305,
            "26": 2.7112457752227783,
            "27": 2.6851348876953125,
            "28": 2.7064719200134277,
            "29": 2.6733598709106445,
            "30": 2.7029128074645996,
            "31": 2.6753580570220947,
            "32": 2.6574981212615967,
            "33": 2.7134032249450684,
            "34": 2.661489725112915,
            "35": 2.6586501598358154,
            "36": 2.65963077545166,
            "37": 2.672985076904297,
            "38": 2.658327102661133,
            "39": 2.645371198654175,
            "40": 2.6593353748321533,
            "41": 2.6823301315307617,
            "42": 2.6230204105377197,
            "43": 2.6486458778381348,
            "44": 2.680811643600464,
            "45": 2.659040689468384,
            "46": 2.6329588890075684,
            "47": 2.622745990753174,
            "48": 2.627995014190674,
            "49": 2.6274917125701904,
            "50": 2.623720645904541,
            "51": 2.611475706100464,
            "52": 2.6306233406066895,
            "53": 2.6243181228637695,
            "54": 2.630488872528076,
            "55": 2.6553213596343994,
            "56": 2.6318089962005615,
            "57": 2.6293482780456543,
            "58": 2.611867904663086,
            "59": 2.615515947341919,
            "60": 2.5961499214172363,
            "61": 2.640744924545288,
            "62": 2.6216373443603516,
            "63": 2.6286134719848633,
            "64": 2.6232876777648926,
            "65": 2.6396641731262207,
            "66": 2.6449108123779297,
            "67": 2.6154398918151855,
            "68": 2.5838241577148438,
            "69": 2.5988683700561523,
            "70": 2.6237521171569824,
            "71": 2.627915859222412,
            "72": 2.6014859676361084,
            "73": 2.6294822692871094,
            "74": 2.6308557987213135,
            "75": 2.62491774559021,
            "76": 2.5663490295410156,
            "77": 2.5956223011016846,
            "78": 2.5833075046539307,
            "79": 2.5826148986816406,
            "80": 2.605762481689453,
            "81": 2.597911834716797,
            "82": 2.5849671363830566,
            "83": 2.608599901199341,
            "84": 2.6233394145965576,
            "85": 2.5937185287475586,
            "86": 2.567758560180664,
            "87": 2.5930516719818115,
            "88": 2.580977439880371,
            "89": 2.595303535461426,
            "90": 2.588501453399658,
            "91": 2.593693256378174,
            "92": 2.5779225826263428,
            "93": 2.613443374633789,
            "94": 2.589177370071411,
            "95": 2.5783016681671143,
            "96": 2.5729806423187256,
            "97": 2.554175853729248,
            "98": 2.5740556716918945,
            "99": 2.591583251953125
        },
        "time_train_student": {
            "0": 0.34868884086608887,
            "1": 0.33295464515686035,
            "2": 0.3270120620727539,
            "3": 0.31840062141418457,
            "4": 0.3274691104888916,
            "5": 0.3245508670806885,
            "6": 0.3218357563018799,
            "7": 0.3198561668395996,
            "8": 0.31461644172668457,
            "9": 0.3207283020019531,
            "10": 0.31871652603149414,
            "11": 0.3176577091217041,
            "12": 0.32067060470581055,
            "13": 0.3075261116027832,
            "14": 0.31081128120422363,
            "15": 0.31601500511169434,
            "16": 0.30700230598449707,
            "17": 0.31780314445495605,
            "18": 0.31917715072631836,
            "19": 0.3144338130950928,
            "20": 0.3152294158935547,
            "21": 0.3130013942718506,
            "22": 0.3113117218017578,
            "23": 0.311964750289917,
            "24": 0.3081376552581787,
            "25": 0.3120088577270508,
            "26": 0.31529760360717773,
            "27": 0.30238962173461914,
            "28": 0.3119688034057617,
            "29": 0.3111393451690674,
            "30": 0.29737353324890137,
            "31": 0.30971479415893555,
            "32": 0.3077878952026367,
            "33": 0.3197035789489746,
            "34": 0.3078634738922119,
            "35": 0.3083689212799072,
            "36": 0.3068387508392334,
            "37": 0.3003838062286377,
            "38": 0.30729174613952637,
            "39": 0.3165874481201172,
            "40": 0.31109046936035156,
            "41": 0.31334352493286133,
            "42": 0.3184835910797119,
            "43": 0.3064558506011963,
            "44": 0.3118758201599121,
            "45": 0.3091597557067871,
            "46": 0.3144798278808594,
            "47": 0.3067286014556885,
            "48": 0.3044617176055908,
            "49": 0.3025050163269043,
            "50": 0.3052642345428467,
            "51": 0.3066272735595703,
            "52": 0.30553340911865234,
            "53": 0.3050708770751953,
            "54": 0.3037428855895996,
            "55": 0.3084712028503418,
            "56": 0.3043513298034668,
            "57": 0.2947981357574463,
            "58": 0.29984521865844727,
            "59": 0.3074665069580078,
            "60": 0.3129415512084961,
            "61": 0.2994542121887207,
            "62": 0.2951176166534424,
            "63": 0.2945215702056885,
            "64": 0.29790163040161133,
            "65": 0.30573153495788574,
            "66": 0.30353307723999023,
            "67": 0.3047752380371094,
            "68": 0.29773449897766113,
            "69": 0.30681347846984863,
            "70": 0.3045320510864258,
            "71": 0.30362534523010254,
            "72": 0.29865479469299316,
            "73": 0.30474019050598145,
            "74": 0.30727624893188477,
            "75": 0.3023085594177246,
            "76": 0.2942087650299072,
            "77": 0.3181767463684082,
            "78": 0.300678014755249,
            "79": 0.3083224296569824,
            "80": 0.3080122470855713,
            "81": 0.3064258098602295,
            "82": 0.3010401725769043,
            "83": 0.30554938316345215,
            "84": 0.3054380416870117,
            "85": 0.30081772804260254,
            "86": 0.30763888359069824,
            "87": 0.3047008514404297,
            "88": 0.30735087394714355,
            "89": 0.3081352710723877,
            "90": 0.30608606338500977,
            "91": 0.30557680130004883,
            "92": 0.29827404022216797,
            "93": 0.29341983795166016,
            "94": 0.299135684967041,
            "95": 0.29625606536865234,
            "96": 0.3051159381866455,
            "97": 0.3006312847137451,
            "98": 0.30680084228515625,
            "99": 0.3120005130767822
        },
        "time_train_distilled": {
            "0": 3.3271644115448,
            "1": 3.0698118209838867,
            "2": 2.997260808944702,
            "3": 2.9647226333618164,
            "4": 2.9367573261260986,
            "5": 2.918020009994507,
            "6": 2.9009945392608643,
            "7": 2.87103271484375,
            "8": 2.8527984619140625,
            "9": 2.825275182723999,
            "10": 2.810131072998047,
            "11": 2.8129384517669678,
            "12": 2.8103549480438232,
            "13": 2.76354718208313,
            "14": 2.75774884223938,
            "15": 2.756988048553467,
            "16": 2.748448133468628,
            "17": 2.7389557361602783,
            "18": 2.742464780807495,
            "19": 2.7288050651550293,
            "20": 1.6332173347473145,
            "21": 1.5512845516204834,
            "22": 1.5441322326660156,
            "23": 1.5409624576568604,
            "24": 1.546839952468872,
            "25": 1.535918951034546,
            "26": 1.541478157043457,
            "27": 1.5379364490509033,
            "28": 1.5307981967926025,
            "29": 1.516361951828003,
            "30": 1.512315034866333,
            "31": 1.4952247142791748,
            "32": 1.4983420372009277,
            "33": 1.5064468383789062,
            "34": 1.5197596549987793,
            "35": 1.5076911449432373,
            "36": 1.5117206573486328,
            "37": 1.5069727897644043,
            "38": 1.5073983669281006,
            "39": 1.4948089122772217,
            "40": 1.4991116523742676,
            "41": 1.505094051361084,
            "42": 1.5046865940093994,
            "43": 1.4948689937591553,
            "44": 1.485527515411377,
            "45": 1.4916467666625977,
            "46": 1.491011381149292,
            "47": 1.4948010444641113,
            "48": 1.4931328296661377,
            "49": 1.4864962100982666,
            "50": 1.476762056350708,
            "51": 1.490264654159546,
            "52": 1.485597848892212,
            "53": 1.479203224182129,
            "54": 1.4922168254852295,
            "55": 1.490785837173462,
            "56": 1.4940590858459473,
            "57": 1.4902195930480957,
            "58": 1.4967129230499268,
            "59": 1.483048677444458,
            "60": 1.4806187152862549,
            "61": 1.4829187393188477,
            "62": 1.4901587963104248,
            "63": 1.4779863357543945,
            "64": 1.4779770374298096,
            "65": 1.4905765056610107,
            "66": 1.5046534538269043,
            "67": 1.4944627285003662,
            "68": 1.487847089767456,
            "69": 1.4888858795166016,
            "70": 1.481644630432129,
            "71": 1.4790091514587402,
            "72": 1.4753103256225586,
            "73": 1.4886887073516846,
            "74": 1.4801740646362305,
            "75": 1.4870758056640625,
            "76": 1.4759318828582764,
            "77": 1.4839696884155273,
            "78": 1.4899656772613525,
            "79": 1.4855389595031738,
            "80": 1.4825661182403564,
            "81": 1.496999740600586,
            "82": 1.4848458766937256,
            "83": 1.4786829948425293,
            "84": 1.476273775100708,
            "85": 1.4825310707092285,
            "86": 1.467468023300171,
            "87": 1.4814400672912598,
            "88": 1.487053632736206,
            "89": 1.4708874225616455,
            "90": 1.4821138381958008,
            "91": 1.4911482334136963,
            "92": 1.4905118942260742,
            "93": 1.4791944026947021,
            "94": 1.4922566413879395,
            "95": 1.4863555431365967,
            "96": 1.4868266582489014,
            "97": 1.4809391498565674,
            "98": 1.476306676864624,
            "99": 1.4863226413726807
        },
        "time_test_teacher": {
            "0": 1.424924373626709,
            "1": 1.4474737644195557,
            "2": 1.4573843479156494,
            "3": 1.4507687091827393,
            "4": 1.4444506168365479,
            "5": 1.4390878677368164,
            "6": 1.4459223747253418,
            "7": 1.4610378742218018,
            "8": 1.4391133785247803,
            "9": 1.43613862991333,
            "10": 1.4438397884368896,
            "11": 1.4424340724945068,
            "12": 1.4425561428070068,
            "13": 1.440251350402832,
            "14": 1.4505202770233154,
            "15": 1.4216687679290771,
            "16": 1.4494035243988037,
            "17": 1.4585216045379639,
            "18": 1.4540648460388184,
            "19": 1.4469830989837646,
            "20": 1.4428646564483643,
            "21": 1.4348323345184326,
            "22": 1.4333176612854004,
            "23": 1.4544227123260498,
            "24": 1.4438672065734863,
            "25": 1.4625146389007568,
            "26": 1.4489850997924805,
            "27": 1.4422218799591064,
            "28": 1.455467939376831,
            "29": 1.4531915187835693,
            "30": 1.4507384300231934,
            "31": 1.4555113315582275,
            "32": 1.4574480056762695,
            "33": 1.4536375999450684,
            "34": 1.4628889560699463,
            "35": 1.462003469467163,
            "36": 1.455583095550537,
            "37": 1.4519038200378418,
            "38": 1.4418308734893799,
            "39": 1.4416790008544922,
            "40": 1.4456532001495361,
            "41": 1.4550650119781494,
            "42": 1.4491875171661377,
            "43": 1.464529037475586,
            "44": 1.4469990730285645,
            "45": 1.4463441371917725,
            "46": 1.4582593441009521,
            "47": 1.4596753120422363,
            "48": 1.4533414840698242,
            "49": 1.4625740051269531,
            "50": 1.451838493347168,
            "51": 1.452542781829834,
            "52": 1.4265165328979492,
            "53": 1.4356365203857422,
            "54": 1.4527008533477783,
            "55": 1.4499564170837402,
            "56": 1.4640042781829834,
            "57": 1.4644720554351807,
            "58": 1.4363229274749756,
            "59": 1.445124626159668,
            "60": 1.4619293212890625,
            "61": 1.4490294456481934,
            "62": 1.451145887374878,
            "63": 1.454472303390503,
            "64": 1.4469475746154785,
            "65": 1.4486651420593262,
            "66": 1.4506053924560547,
            "67": 1.4795398712158203,
            "68": 1.418227195739746,
            "69": 1.449059009552002,
            "70": 1.4430296421051025,
            "71": 1.430448293685913,
            "72": 1.4556291103363037,
            "73": 1.4628629684448242,
            "74": 1.4614787101745605,
            "75": 1.4826691150665283,
            "76": 1.4585392475128174,
            "77": 1.4466166496276855,
            "78": 1.4603443145751953,
            "79": 1.4588770866394043,
            "80": 1.4547903537750244,
            "81": 1.456836462020874,
            "82": 1.446415901184082,
            "83": 1.4526069164276123,
            "84": 1.4779884815216064,
            "85": 1.4588358402252197,
            "86": 1.4382894039154053,
            "87": 1.4637844562530518,
            "88": 1.4579558372497559,
            "89": 1.4530377388000488,
            "90": 1.4394092559814453,
            "91": 1.4524123668670654,
            "92": 1.460447072982788,
            "93": 1.4508326053619385,
            "94": 1.4449381828308105,
            "95": 1.4601280689239502,
            "96": 1.4461438655853271,
            "97": 1.4551498889923096,
            "98": 1.4566051959991455,
            "99": 1.4580121040344238
        },
        "time_test_student": {
            "0": 0.06295156478881836,
            "1": 0.06323003768920898,
            "2": 0.06438970565795898,
            "3": 0.06433916091918945,
            "4": 0.0664663314819336,
            "5": 0.06728863716125488,
            "6": 0.07780575752258301,
            "7": 0.0632331371307373,
            "8": 0.0651707649230957,
            "9": 0.0641181468963623,
            "10": 0.0628349781036377,
            "11": 0.0640256404876709,
            "12": 0.06814026832580566,
            "13": 0.07308840751647949,
            "14": 0.06299042701721191,
            "15": 0.06593751907348633,
            "16": 0.0657968521118164,
            "17": 0.0638735294342041,
            "18": 0.06271052360534668,
            "19": 0.07115292549133301,
            "20": 0.07353830337524414,
            "21": 0.07413840293884277,
            "22": 0.06432366371154785,
            "23": 0.08786225318908691,
            "24": 0.06349515914916992,
            "25": 0.06331229209899902,
            "26": 0.06313657760620117,
            "27": 0.06329464912414551,
            "28": 0.06425690650939941,
            "29": 0.06414389610290527,
            "30": 0.06313133239746094,
            "31": 0.06374239921569824,
            "32": 0.06311798095703125,
            "33": 0.10133075714111328,
            "34": 0.06811189651489258,
            "35": 0.06602716445922852,
            "36": 0.06356692314147949,
            "37": 0.07319998741149902,
            "38": 0.06287837028503418,
            "39": 0.07581901550292969,
            "40": 0.06450796127319336,
            "41": 0.06577420234680176,
            "42": 0.06350946426391602,
            "43": 0.07239484786987305,
            "44": 0.07189559936523438,
            "45": 0.07738018035888672,
            "46": 0.06298422813415527,
            "47": 0.06989359855651855,
            "48": 0.06477713584899902,
            "49": 0.06493473052978516,
            "50": 0.06361126899719238,
            "51": 0.06362342834472656,
            "52": 0.06604480743408203,
            "53": 0.06398582458496094,
            "54": 0.06361079216003418,
            "55": 0.0661466121673584,
            "56": 0.06271004676818848,
            "57": 0.06474614143371582,
            "58": 0.06635594367980957,
            "59": 0.0747981071472168,
            "60": 0.07248282432556152,
            "61": 0.06267237663269043,
            "62": 0.06522536277770996,
            "63": 0.06303286552429199,
            "64": 0.06528806686401367,
            "65": 0.06659841537475586,
            "66": 0.06352663040161133,
            "67": 0.06315422058105469,
            "68": 0.06351137161254883,
            "69": 0.0651094913482666,
            "70": 0.06358003616333008,
            "71": 0.06783604621887207,
            "72": 0.06334805488586426,
            "73": 0.06647062301635742,
            "74": 0.06302499771118164,
            "75": 0.06667661666870117,
            "76": 0.06648397445678711,
            "77": 0.06316947937011719,
            "78": 0.06838607788085938,
            "79": 0.06751561164855957,
            "80": 0.06538128852844238,
            "81": 0.0632169246673584,
            "82": 0.06227445602416992,
            "83": 0.06329154968261719,
            "84": 0.06264066696166992,
            "85": 0.06300187110900879,
            "86": 0.06289172172546387,
            "87": 0.06271123886108398,
            "88": 0.06302618980407715,
            "89": 0.06604647636413574,
            "90": 0.06659054756164551,
            "91": 0.06305694580078125,
            "92": 0.06359410285949707,
            "93": 0.06280922889709473,
            "94": 0.06306982040405273,
            "95": 0.06315016746520996,
            "96": 0.06391334533691406,
            "97": 0.06505775451660156,
            "98": 0.06567716598510742,
            "99": 0.0730900764465332
        },
        "time_test_distilled": {
            "0": 1.424924373626709,
            "1": 1.4474737644195557,
            "2": 1.4573843479156494,
            "3": 1.4507687091827393,
            "4": 1.4444506168365479,
            "5": 1.4390878677368164,
            "6": 1.4459223747253418,
            "7": 1.4610378742218018,
            "8": 1.4391133785247803,
            "9": 1.43613862991333,
            "10": 1.4438397884368896,
            "11": 1.4424340724945068,
            "12": 1.4425561428070068,
            "13": 1.440251350402832,
            "14": 1.4505202770233154,
            "15": 1.4216687679290771,
            "16": 1.4494035243988037,
            "17": 1.4585216045379639,
            "18": 1.4540648460388184,
            "19": 1.4469830989837646,
            "20": 0.30548572540283203,
            "21": 0.3127617835998535,
            "22": 0.30858755111694336,
            "23": 0.31658196449279785,
            "24": 0.3130049705505371,
            "25": 0.32291150093078613,
            "26": 0.32278966903686523,
            "27": 0.3218221664428711,
            "28": 0.33510446548461914,
            "29": 0.31351399421691895,
            "30": 0.3215169906616211,
            "31": 0.33288145065307617,
            "32": 0.32370662689208984,
            "33": 0.3263399600982666,
            "34": 0.3198585510253906,
            "35": 0.3228790760040283,
            "36": 0.3144643306732178,
            "37": 0.3190279006958008,
            "38": 0.32552075386047363,
            "39": 0.3213615417480469,
            "40": 0.3166074752807617,
            "41": 0.31787586212158203,
            "42": 0.3160562515258789,
            "43": 0.32201433181762695,
            "44": 0.33000731468200684,
            "45": 0.3282904624938965,
            "46": 0.3304250240325928,
            "47": 0.3237326145172119,
            "48": 0.3222625255584717,
            "49": 0.328080415725708,
            "50": 0.3226511478424072,
            "51": 0.3174252510070801,
            "52": 0.3215618133544922,
            "53": 0.323793888092041,
            "54": 0.3212275505065918,
            "55": 0.3345654010772705,
            "56": 0.3247859477996826,
            "57": 0.3243544101715088,
            "58": 0.3332176208496094,
            "59": 0.31619930267333984,
            "60": 0.31292152404785156,
            "61": 0.3218815326690674,
            "62": 0.3150782585144043,
            "63": 0.3230156898498535,
            "64": 0.33038830757141113,
            "65": 0.32646989822387695,
            "66": 0.3260457515716553,
            "67": 0.3280601501464844,
            "68": 0.3231642246246338,
            "69": 0.3236973285675049,
            "70": 0.33030009269714355,
            "71": 0.3275001049041748,
            "72": 0.32524585723876953,
            "73": 0.318164587020874,
            "74": 0.3247509002685547,
            "75": 0.3311653137207031,
            "76": 0.32466840744018555,
            "77": 0.32677149772644043,
            "78": 0.33159708976745605,
            "79": 0.32587265968322754,
            "80": 0.3197009563446045,
            "81": 0.3278467655181885,
            "82": 0.32511138916015625,
            "83": 0.3240666389465332,
            "84": 0.32347774505615234,
            "85": 0.32430481910705566,
            "86": 0.332369327545166,
            "87": 0.32821202278137207,
            "88": 0.32450175285339355,
            "89": 0.3218367099761963,
            "90": 0.33036184310913086,
            "91": 0.32727861404418945,
            "92": 0.3333120346069336,
            "93": 0.3292248249053955,
            "94": 0.3222033977508545,
            "95": 0.3293488025665283,
            "96": 0.3195919990539551,
            "97": 0.31997203826904297,
            "98": 0.3191359043121338,
            "99": 0.3361020088195801
        }
    }
}